{
	"name": "MacOS Modern - Xcode Default",
	"$schema": "vscode://schemas/color-theme",
	"type": "light",
	"tokenColors": [
		{
			"name": "Comment",
			"scope": "comment",
			"settings": {
				"foreground": "#008E00"
			}
		},
		{
			"name": "Preprocessor Statements",
			"scope": [
				"meta.preprocessor",
				"keyword.control.import"
			],
			"settings": {
				"foreground": "#7D4726"
			}
		},
		{
			"name": "String",
			"scope": "string",
			"settings": {
				"foreground": "#DF0002"
			}
		},
		{
			"name": "Number",
			"scope": "constant.numeric",
			"settings": {
				"foreground": "#3A00DC"
			}
		},
		{
			"name": "Built-in constant",
			"scope": "constant.language",
			"settings": {
				"foreground": "#C800A4"
			}
		},
		{
			"name": "User-defined constant",
			"scope": [
				"constant.character",
				"constant.other"
			],
			"settings": {
				"foreground": "#275A5E"
			}
		},
		{
			"name": "Variable",
			"scope": [
				"variable.language",
				"variable.other"
			],
			"settings": {
				"foreground": "#C800A4"
			}
		},
		{
			"name": "Keyword",
			"scope": "keyword",
			"settings": {
				"foreground": "#C800A4"
			}
		},
		{
			"name": "Storage",
			"scope": "storage",
			"settings": {
				"foreground": "#C900A4"
			}
		},
		{
			"name": "Class name",
			"scope": "entity.name.class",
			"settings": {
				"foreground": "#438288"
			}
		},
		{
			"name": "Inherited class",
			"scope": "entity.other.inherited-class",
			"settings": {}
		},
		{
			"name": "Function name",
			"scope": "entity.name.function",
			"settings": {}
		},
		{
			"name": "Function argument",
			"scope": "variable.parameter",
			"settings": {}
		},
		{
			"name": "Tag name",
			"scope": "entity.name.tag",
			"settings": {
				"foreground": "#790EAD"
			}
		},
		{
			"name": "Tag attribute",
			"scope": "entity.other.attribute-name",
			"settings": {
				"foreground": "#450084"
			}
		},
		{
			"name": "Library function",
			"scope": "support.function",
			"settings": {
				"foreground": "#450084"
			}
		},
		{
			"name": "Library constant",
			"scope": "support.constant",
			"settings": {
				"foreground": "#450084"
			}
		},
		{
			"name": "Library class/type",
			"scope": [
				"support.type",
				"support.class"
			],
			"settings": {
				"foreground": "#790EAD"
			}
		},
		{
			"name": "Library variable",
			"scope": "support.other.variable",
			"settings": {
				"foreground": "#790EAD"
			}
		},
		{
			"name": "Invalid",
			"scope": "invalid",
			"settings": {}
		},
		{
			"scope": "token.info-token",
			"settings": {
				"foreground": "#316bcd"
			}
		},
		{
			"scope": "token.warn-token",
			"settings": {
				"foreground": "#cd9731"
			}
		},
		{
			"scope": "token.error-token",
			"settings": {
				"foreground": "#cd3131"
			}
		},
		{
			"scope": "token.debug-token",
			"settings": {
				"foreground": "#800080"
			}
		}
	]
}